{"singlePage": [], "startSite": "", "filingNum": "", "onePageListNum": 20, "commentLabelColor": "#006b75", "yearColorList": ["#bc4c00", "#0969da", "#1f883d", "#A333D0"], "i18n": "CN", "themeMode": "manual", "dayTheme": "light", "nightTheme": "dark", "urlMode": "pinyin", "script": "", "style": "", "head": "", "indexScript": "", "indexStyle": "", "bottomText": "", "showPostSource": 1, "iconList": {}, "UTC": 8, "rssSplit": "sentence", "exlink": {}, "needComment": 1, "allHead": "", "title": "China Kitchen Appliance OEM & ODM Resource Center", "displayTitle": "Yolec Electric", "subTitle": "Helping importers, distributors, retailers and private label brands source reliable kitchen appliances from China. Explore OEM & ODM manufacturing guides, supplier insights, product expertise and factory best practices for smarter sourcing decisions.", "avatarUrl": "https://avatars.githubusercontent.com/u/298971764?v=4", "homeUrl": "https://www.yolec-electronics.com/", "GMEEK_VERSION": "last", "postListJson": {"P1": {"htmlDir": "docs/post/Hi, I'm Lisa\ud83d\udc4b.html", "labels": ["documentation"], "postTitle": "Hi, I'm Lisa\ud83d\udc4b", "postUrl": "post/Hi%2C%20I%27m%20Lisa%F0%9F%91%8B.html", "postSourceUrl": "https://github.com/yoleckitchen/yoleckitchen.github.io/issues/1", "commentNum": 0, "wordCount": 757, "description": "I'm an OEM & ODM consultant specializing in small kitchen appliances.\n\nFor over 10 years, I have been helping importers, wholesalers, retailers, and private label brands develop reliable kitchen appliances from China.\n\n## Our Product Line\n\n- Electric Kettle\n- Gooseneck Kettle\n- Rice Cooker\n- Electric Pressure Cooker\n- Electric Lunch Box\n- Hand Blender\n\n## Why Work With Us?\n\n\u2714 Established in 2016\n\n\u2714 Exported to 40+ countries\n\n\u2714 CE Certified\n\n\u2714 RoHS Compliant\n\n\u2714 OEM & ODM Services\n\n\u2714 Low MOQ\n\n## Industries\n\n- Retail\n- Supermarket\n- Online Sellers\n- Amazon Brands\n- Kitchen Brands\n- Importers\n\n## Contact\n\n\ud83c\udf0d https://www.yolec-electronics.com/\n\n\ud83d\udce7 [Adrian@yolec-electronics.com](mailto:Adrian@yolec-electronics.com)\n\nLet's build your next product together.\u3002", "top": 0, "createdAt": 1782980220, "style": "", "script": "", "head": "", "ogImage": "https://avatars.githubusercontent.com/u/298971764?v=4", "createdDate": "2026-07-02", "dateLabelColor": "#1f883d"}, "P2": {"htmlDir": "docs/post/China Kitchen Appliance Manufacturer Overview.html", "labels": ["documentation"], "postTitle": "China Kitchen Appliance Manufacturer Overview", "postUrl": "post/China%20Kitchen%20Appliance%20Manufacturer%20Overview.html", "postSourceUrl": "https://github.com/yoleckitchen/yoleckitchen.github.io/issues/2", "commentNum": 0, "wordCount": 5421, "description": "Over the past few years, I've been involved in sourcing kitchen appliances from China for private label and OEM projects. One thing I've noticed is that many buyers search for **'China kitchen appliance manufacturer'** expecting to find a simple list of factories, but the reality is much more complicated.\n\nNot every manufacturer is the right partner, and not every trading company is a bad choice. It really depends on what you're trying to build.\n\nThis post is a quick overview for anyone looking for a reliable manufacturing partner in China.\n\n---\n\n## Why China Is Still the First Choice\n\nEven with rising labor costs, China remains the largest manufacturing base for small kitchen appliances.\n\nThe biggest advantages are:\n\n- Complete supply chains\n- Mature production experience\n- Competitive tooling costs\n- Flexible OEM and ODM services\n- Stable export capability\n- International certifications for different markets\n\nMany factories already produce products for well-known international brands, although most cannot publicly disclose those partnerships because of NDAs.\n\n---\n\n## Common Kitchen Appliances Manufactured in China\n\nA typical manufacturer may specialize in one category or several related products.\n\nPopular categories include:\n\n- Electric kettles\n- Gooseneck coffee kettles\n- Rice cookers\n- Electric pressure cookers\n- Multi cookers\n- Electric lunch boxes\n- Hand mixers\n- Food processors\n- Air fryers\n- Toasters\n- Coffee makers\n\nFactories focusing on fewer product categories usually have deeper engineering experience than those trying to produce everything.\n\n---\n\n## OEM vs ODM\n\nThis is one question that comes up in almost every sourcing discussion.\n\n### OEM\n\nOEM works well if you already have:\n\n- Product specifications\n- Brand identity\n- Packaging design\n- Market positioning\n\nThe factory manufactures according to your requirements.\n\n---\n\n### ODM\n\nODM is usually faster.\n\nThe manufacturer already has existing product designs, and you customize:\n\n- Logo\n- Color\n- Packaging\n- User manual\n- Small appearance details\n\nFor many new brands, ODM is the fastest way to enter the market.\n\n---\n\n## Things Worth Checking Before Choosing a Factory\n\nPrice matters, but it's definitely not everything.\n\nHere are a few things I always ask suppliers.\n\n### Manufacturing experience\n\nHow long have they been producing this category?\n\nFive years and fifteen years can make a huge difference in process control.\n\n---\n\n### Production capacity\n\nCan they handle your future growth?\n\nMany suppliers look great during sampling but struggle with larger production runs.\n\n---\n\n### Quality control\n\nAsk about:\n\n- Incoming material inspection\n- Assembly inspection\n- Electrical safety testing\n- Final product inspection\n- Aging tests\n\nGood factories are usually happy to explain their QC process.\n\n---\n\n### Certifications\n\nDifferent markets require different certifications.\n\nExamples include:\n\n- CE\n- CB\n- GS\n- ETL\n- UKCA\n- LFGB\n- RoHS\n\nAlways confirm certifications before placing an order.\n\n---\n\n### Product development\n\nIf you're building a long-term brand, engineering support becomes very important.\n\nAsk questions like:\n\n- Can they modify existing molds?\n- Can they develop new products?\n- Do they provide industrial design support?\n- How long does tooling normally take?\n\n---\n\n## Minimum Order Quantity\n\nMOQ varies quite a bit.\n\nTypical ranges look something like this:\n\n| Product | Typical MOQ |\n| -------- | ----------- |\n| Electric kettle | 500-1000 pcs |\n| Rice cooker | 500-1000 pcs |\n| Pressure cooker | 500-1000 pcs |\n| Hand mixer | 1000 pcs |\n\nSome factories may offer lower quantities for trial orders, especially for existing models.\n\n---\n\n## Don't Judge a Factory Only by Price\n\nA quotation that is 10% lower can sometimes become much more expensive later.\n\nI've seen buyers run into issues like:\n\n- Delayed production\n- Poor packaging\n- High defect rates\n- Weak after-sales support\n- Missing certifications\n\nA slightly higher unit price from a reliable manufacturer often saves money over the life of the project.\n\n---\n\n## Communication Matters More Than Most People Expect\n\nOne thing that's often overlooked is communication.\n\nA supplier that replies clearly, asks detailed questions, and confirms specifications usually makes the whole project much smoother.\n\nMisunderstandings during development are much more expensive than spending an extra day confirming details.\n\n---\n\n## Long-Term Partnerships Usually Work Better\n\nMany successful importers don't switch factories every year.\n\nOnce both sides understand each other's quality standards, packaging requirements, shipping process, and product expectations, future projects become much easier.\n\nA stable manufacturing partner often brings more value than simply finding the lowest quotation every time.\n\n---\n\n## Final Thoughts\n\nFinding a reliable China kitchen appliance manufacturer isn't just about comparing prices.\n\nIt's about choosing a supplier that can consistently deliver quality products, communicate well, and support your business as it grows.\n\nIf you're sourcing products like:\n\n- Electric kettles\n- Gooseneck coffee kettles\n- Rice cookers\n- Electric pressure cookers\n- Electric lunch boxes\n- Hand mixers\n\nI'd be happy to exchange sourcing experiences or discuss OEM/ODM manufacturing.\n\n**Company:** YOLEC Electric\n\n**Website:** https://www.yolec-electronics.com\n\n**Email:** Adrian@yolec-electronics.com\n\n**WhatsApp:** +86 13922332584\u3002", "top": 0, "createdAt": 1783264800, "style": "", "script": "", "head": "", "ogImage": "https://avatars.githubusercontent.com/u/298971764?v=4", "createdDate": "2026-07-05", "dateLabelColor": "#1f883d"}, "P3": {"htmlDir": "docs/post/How to Choose a Reliable Kitchen Appliance Manufacturer in China.html", "labels": ["documentation"], "postTitle": "How to Choose a Reliable Kitchen Appliance Manufacturer in China", "postUrl": "post/How%20to%20Choose%20a%20Reliable%20Kitchen%20Appliance%20Manufacturer%20in%20China.html", "postSourceUrl": "https://github.com/yoleckitchen/yoleckitchen.github.io/issues/3", "commentNum": 0, "wordCount": 6195, "description": "Finding a kitchen appliance manufacturer in China sounds easy until you actually start contacting suppliers.\n\nOn paper, many factories look almost identical. Similar product photos. Similar certificates. Similar prices. But once you begin discussing samples, customization, or production schedules, the differences become obvious.\n\nAfter working with several manufacturers over the years, here are a few things that have proven to matter much more than a low quotation.\n\n---\n\n## Don't Start with Price\n\nIt's tempting to sort quotations from lowest to highest.\n\nMost buyers do it.\n\nThe problem is that the cheapest supplier isn't always the manufacturer with the lowest production cost. Sometimes it's simply the one willing to cut corners.\n\nA slightly lower price may also mean:\n\n- thinner stainless steel\n- lower-grade heating elements\n- cheaper thermostats\n- weaker packaging\n- less testing before shipment\n\nThose savings often disappear once warranty claims and customer complaints start coming in.\n\n---\n\n## Make Sure You're Talking to a Real Manufacturer\n\nNot every supplier on Alibaba or Google owns a factory.\n\nSome are trading companies.\n\nThere's nothing wrong with trading companies if they provide good service, but if you're planning long-term OEM projects, it's worth confirming who actually makes the products.\n\nA few simple questions usually tell you a lot.\n\nFor example:\n\n- How many production lines do you have?\n- Can I see your workshop?\n- Do you produce this product yourself?\n- Can you arrange a factory video call?\n\nReal manufacturers usually answer these questions without hesitation.\n\n---\n\n## Look Beyond the Product Photos\n\nAnyone can download attractive product images.\n\nInstead, ask about the production process.\n\nQuestions like these often reveal how experienced a supplier really is.\n\n- How is incoming material inspected?\n- What safety tests are performed?\n- How long is the aging test?\n- How are heating elements tested?\n- What happens if a batch fails inspection?\n\nExperienced factories usually enjoy talking about production because that's what they do every day.\n\n---\n\n## Experience in Your Product Category Matters\n\nA factory making electric kettles for ten years is usually a safer choice than one that started producing them six months ago.\n\nThe same goes for:\n\n- Rice cookers\n- Electric pressure cookers\n- Hand mixers\n- Electric lunch boxes\n\nEvery category has different engineering challenges.\n\nSomeone specializing in coffee kettles understands pouring control.\n\nA rice cooker factory understands heating algorithms.\n\nCategory experience saves a lot of time during development.\n\n---\n\n## Ask About OEM and ODM Support\n\nSome buyers already have finished product designs.\n\nOthers only have an idea.\n\nThat's where OEM and ODM become different.\n\nIf you're still deciding which model fits your market, it's worth reading a practical explanation of **OEM and ODM kitchen appliance manufacturing** before requesting quotations.\n\nUnderstanding the difference early can save weeks of unnecessary communication.\n\n---\n\n## Communication Can Save More Money Than Negotiation\n\nOne thing I've learned is that communication quality often predicts production quality.\n\nA supplier who asks detailed questions usually causes fewer problems later.\n\nFor example:\n\n> Which market are you selling to?\n\n> Which certifications are required?\n\n> What's your target retail price?\n\n> Will the logo be laser engraved or silk printed?\n\nThose questions may seem small, but they prevent expensive mistakes.\n\n---\n\n## Samples Tell You More Than Catalogs\n\nNever make a decision based only on a PDF catalog.\n\nRequest samples.\n\nWhen they arrive, pay attention to details like:\n\n- Surface finish\n- Lid fit\n- Switch feel\n- Heating speed\n- Noise level\n- Handle comfort\n- Packaging quality\n\nSometimes two kettles look identical online but feel completely different in real life.\n\n---\n\n## Certifications Should Match Your Market\n\nDifferent countries require different approvals.\n\nDepending on where you're selling, you may need:\n\n- CE\n- CB\n- GS\n- ETL\n- UKCA\n- LFGB\n- RoHS\n\nDon't assume every certificate shown on a website applies to every product.\n\nAlways verify.\n\n---\n\n## Production Capacity Matters\n\nSmall trial orders are usually easy.\n\nLarge repeat orders are where capacity becomes important.\n\nAsk questions like:\n\n- Monthly production capacity\n- Peak season lead time\n- Number of assembly lines\n- Number of QC inspectors\n\nA factory that can only produce 8,000 units per month may not support your future growth.\n\n---\n\n## Don't Ignore Product Development\n\nMany buyers focus only on today's order.\n\nSuccessful brands usually think further ahead.\n\nAsk whether the factory can support:\n\n- New mold development\n- Appearance modifications\n- Color customization\n- New packaging\n- Structural improvements\n\nA manufacturer that supports product development becomes much more valuable over time.\n\n---\n\n## Visit If You Can\n\nNothing replaces seeing a factory in person.\n\nEven one afternoon can tell you things that dozens of emails cannot.\n\nYou'll notice:\n\n- Production organization\n- Worker experience\n- Cleanliness\n- Warehouse management\n- Testing equipment\n- Packaging standards\n\nIf visiting isn't possible, a live video tour is still much better than relying on marketing photos.\n\n---\n\n## Build Relationships, Not Just Purchase Orders\n\nMany successful importers work with the same manufacturer for years.\n\nOnce both sides understand product expectations, packaging standards, and quality requirements, future projects become much smoother.\n\nChanging suppliers every order often creates more problems than it solves.\n\n---\n\n## Final Thoughts\n\nChoosing a reliable kitchen appliance manufacturer in China isn't about finding the lowest quotation.\n\nIt's about finding a partner who understands your product, communicates clearly, maintains consistent quality, and can grow with your business.\n\nIf you're still comparing suppliers, reading a few detailed resources on **China kitchen appliance manufacturers** before making a decision can help you ask better questions and avoid common sourcing mistakes.\n\nThe more prepared you are before contacting factories, the easier the entire OEM or ODM process becomes.\u3002", "top": 0, "createdAt": 1783404743, "style": "", "script": "", "head": "", "ogImage": "https://avatars.githubusercontent.com/u/298971764?v=4", "createdDate": "2026-07-07", "dateLabelColor": "#1f883d"}, "P4": {"htmlDir": "docs/post/OEM vs ODM- What Is the Difference for Kitchen Appliances-.html", "labels": ["documentation"], "postTitle": "OEM vs ODM: What Is the Difference for Kitchen Appliances?", "postUrl": "post/OEM%20vs%20ODM-%20What%20Is%20the%20Difference%20for%20Kitchen%20Appliances-.html", "postSourceUrl": "https://github.com/yoleckitchen/yoleckitchen.github.io/issues/4", "commentNum": 0, "wordCount": 7137, "description": "When buyers start sourcing kitchen appliances from China, one of the first questions they usually ask is:\n\n'Should I choose OEM or ODM?'\n\nAt first glance, the difference looks simple.\n\nOEM means the factory makes your product.\n\nODM means the factory helps develop the product.\n\nBut in real projects, the difference is not always that clear.\n\nFor kitchen appliances, choosing between OEM and ODM affects:\n\n- Development time\n- Product cost\n- Customization level\n- Production risk\n- Market positioning\n\nThis article explains the difference from a practical sourcing perspective.\n\n---\n\n## What Is OEM Manufacturing?\n\nOEM stands for **Original Equipment Manufacturer**.\n\nIn an OEM project, the buyer usually provides the product requirements, design, or specifications.\n\nThe manufacturer produces according to those requirements.\n\nFor example:\n\nYou already have an electric kettle design.\n\nYou decide:\n\n- Product appearance\n- Materials\n- Functions\n- Packaging\n- Brand identity\n\nThe factory handles:\n\n- Production\n- Assembly\n- Quality control\n- Testing\n\nOEM gives brands more control over the final product.\n\n---\n\n## What Is ODM Manufacturing?\n\nODM stands for **Original Design Manufacturer**.\n\nIn an ODM project, the manufacturer already has product designs or technical solutions.\n\nThe buyer can customize the product based on existing models.\n\nCommon customization options include:\n\n- Logo\n- Color\n- Packaging\n- User manual\n- Small design changes\n\nODM is popular among new brands because it reduces development time.\n\nInstead of creating everything from zero, you start with a proven product platform.\n\n---\n\n## OEM vs ODM: A Simple Comparison\n\n| | OEM | ODM |\n|---|---|---|\n| Product design | Buyer provides | Factory provides |\n| Development time | Longer | Faster |\n| Customization | Higher | Medium |\n| Investment | Usually higher | Usually lower |\n| Suitable for | Established brands | New brands |\n| Product uniqueness | Higher | Depends on customization |\n\n---\n\n## Why Many New Brands Choose ODM\n\nLaunching a kitchen appliance brand is not easy.\n\nMany new companies have good marketing ideas but limited engineering experience.\n\nDeveloping a completely new product requires:\n\n- Industrial design\n- Engineering support\n- Mold development\n- Testing\n- Certification\n- Trial production\n\nThis can take months.\n\nODM allows brands to enter the market faster.\n\nFor example, a new coffee equipment brand may start with an existing gooseneck kettle platform, customize the appearance and packaging, then test market demand.\n\nAfter gaining experience, they may move toward full OEM development.\n\n---\n\n## Why Established Brands Often Prefer OEM\n\nLarge brands usually already understand their customers.\n\nThey know:\n\n- What features are needed\n- What price level works\n- What design matches their brand\n\nFor them, OEM provides more control.\n\nThey may need:\n\n- Unique product structures\n- Special materials\n- Custom functions\n- Exclusive molds\n\nThe goal is not just selling another product.\n\nThe goal is creating something competitors cannot easily copy.\n\n---\n\n## A Common Mistake: Thinking ODM Means No Customization\n\nSome buyers think ODM means:\n\n'Just put my logo on an existing product.'\n\nThat is not always true.\n\nA good ODM manufacturer can often support:\n\n- Color changes\n- Housing modifications\n- Function adjustments\n- Packaging development\n- Market-specific requirements\n\nThe level of customization depends on the factory's engineering capability.\n\n---\n\n## Another Mistake: Choosing OEM Too Early\n\nSome startups immediately want a completely new product.\n\nIt sounds attractive:\n\n'Nobody else has this design.'\n\nBut new product development also means more risk.\n\nCommon problems include:\n\n- Higher tooling cost\n- Longer development time\n- Unexpected design problems\n- More testing requirements\n\nSometimes starting with ODM is actually the smarter business decision.\n\n---\n\n## How to Decide Between OEM and ODM?\n\nAsk yourself these questions.\n\n### Do you already have a product design?\n\nIf yes:\n\nOEM may be a better choice.\n\n---\n\n### Are you testing a new market?\n\nIf yes:\n\nODM can reduce risk.\n\n---\n\n### Do you need a unique product?\n\nIf your strategy depends on differentiation:\n\nOEM provides more flexibility.\n\n---\n\n### Is speed important?\n\nIf you want to launch quickly:\n\nODM is usually faster.\n\n---\n\n## OEM and ODM Capability Depends on the Factory\n\nThis is something many buyers overlook.\n\nTwo factories may both say:\n\n'We provide OEM and ODM.'\n\nBut their actual ability can be very different.\n\nA capable manufacturer should be able to discuss:\n\n- Product structure\n- Materials\n- Production methods\n- Testing requirements\n- Certification needs\n\nThey should not only talk about prices.\n\n---\n\n## Kitchen Appliances Require More Than Assembly\n\nFor products like:\n\n- Electric kettles\n- Rice cookers\n- Electric pressure cookers\n- Electric lunch boxes\n- Hand mixers\n\nmanufacturing involves many technical areas.\n\nIncluding:\n\n- Heating systems\n- Electrical safety\n- Temperature control\n- Plastic injection\n- Metal processing\n- Component matching\n\nA supplier with real engineering experience can help avoid problems before mass production.\n\n---\n\n## OEM, ODM, or Private Label?\n\nMany buyers also search for **private label kitchen appliance manufacturers**.\n\nPrivate label is closely related to ODM.\n\nUsually, private label means:\n\n- Existing product model\n- Your brand logo\n- Your packaging\n- Your market positioning\n\nIt is one of the fastest ways for retailers and online brands to launch kitchen appliances.\n\n---\n\n## What Should You Ask a Manufacturer?\n\nBefore starting cooperation, ask:\n\n1. Do you mainly produce OEM or ODM projects?\n\n2. Can you modify existing products?\n\n3. Can you develop new molds?\n\n4. What is your minimum order quantity?\n\n5. What certifications are available?\n\n6. Can you provide samples before mass production?\n\n7. How do you control quality?\n\nThese questions help you understand whether the supplier matches your project.\n\n---\n\n## Final Thoughts\n\nThere is no absolute winner between OEM and ODM.\n\nThe better choice depends on your business stage.\n\nChoose OEM when you need:\n\n- Maximum control\n- Unique products\n- Long-term product development\n\nChoose ODM when you need:\n\n- Faster launch\n- Lower development risk\n- Existing product solutions\n\nMany successful brands actually use both.\n\nThey start with ODM to test the market, then move toward OEM once they understand customer demand.\n\nFor more practical information about **kitchen appliance OEM and ODM manufacturing in China**, you can explore our factory resources here:\n\n[China Kitchen Appliance OEM & ODM Manufacturer](https://www.yolec-electronics.com/)\n\n---\n\n## About YOLEC Electric\n\nYOLEC Electric provides OEM and ODM manufacturing solutions for global kitchen appliance brands.\n\nMain product categories:\n\n- Electric kettles\n- Gooseneck coffee kettles\n- Rice cookers\n- Electric pressure cookers\n- Electric lunch boxes\n- Hand mixers\n\nWe support importers, distributors, and private label brands with product development and manufacturing services.\n\nWebsite:\nhttps://www.yolec-electronics.com/\n\nEmail:\nAdrian@yolec-electronics.com\n\nWhatsApp:\n+86 13922332584\u3002", "top": 0, "createdAt": 1783562772, "style": "", "script": "", "head": "", "ogImage": "https://avatars.githubusercontent.com/u/298971764?v=4", "createdDate": "2026-07-09", "dateLabelColor": "#1f883d"}, "P5": {"htmlDir": "docs/post/Why Global Brands Source Kitchen Appliances from China.html", "labels": ["documentation"], "postTitle": "Why Global Brands Source Kitchen Appliances from China", "postUrl": "post/Why%20Global%20Brands%20Source%20Kitchen%20Appliances%20from%20China.html", "postSourceUrl": "https://github.com/yoleckitchen/yoleckitchen.github.io/issues/5", "commentNum": 1, "wordCount": 7922, "description": "When global brands look for a kitchen appliance manufacturer, China is usually one of the first markets they consider.\n\nA simple Google search for 'kitchen appliance manufacturer China' will show thousands of suppliers.\n\nBut the real question is not:\n\n'Why are there so many factories in China?'\n\nThe better question is:\n\n'Why do so many brands continue choosing China after comparing different manufacturing locations?'\n\nOver the years, some buyers have considered moving production to other regions, including Southeast Asia. This is understandable. Supply chains are changing, labor costs are changing, and companies want more flexibility.\n\nHowever, for small kitchen appliances, China still remains one of the strongest manufacturing bases in the world.\n\nThe reason is not only about price.\n\n---\n\n## China Has a Complete Kitchen Appliance Supply Chain\n\nA kitchen appliance is not made by one factory alone.\n\nMany people outside the industry imagine a factory as a building where workers simply assemble products.\n\nIn reality, a finished product depends on many suppliers working together.\n\nFor example, an electric kettle may involve:\n\n- Stainless steel suppliers\n- Plastic injection factories\n- Heating element manufacturers\n- Electronic component suppliers\n- PCB suppliers\n- Packaging companies\n- Testing laboratories\n\nChina's biggest advantage is that these suppliers are already connected.\n\nWhen a factory needs to solve a production problem, it can usually find a solution quickly.\n\nThis is especially important for OEM and ODM projects.\n\n---\n\n## Manufacturing Experience Matters More Than Low Labor Cost\n\nA few years ago, many buyers mainly focused on production cost.\n\nToday, the situation is different.\n\nA lower factory price does not always mean a lower total cost.\n\nA product can become expensive because of:\n\n- High defect rates\n- Production delays\n- Poor communication\n- Failed certification tests\n- Customer returns\n\nExperienced manufacturers understand these problems because they have dealt with them before.\n\nFor kitchen appliances, experience is often a hidden advantage.\n\n---\n\n## Why Not Move Everything to Southeast Asia?\n\nThis is a question many international buyers ask.\n\nCountries such as Vietnam, Thailand, and Malaysia have become important manufacturing locations.\n\nThey offer advantages like:\n\n- Competitive labor costs\n- Trade benefits\n- Growing industrial infrastructure\n\nFor some industries, especially large-volume standardized production, Southeast Asia can be a good choice.\n\nBut kitchen appliances have their own challenges.\n\nProducts like:\n\n- Electric kettles\n- Rice cookers\n- Pressure cookers\n- Coffee kettles\n- Hand mixers\n\nrequire a combination of:\n\n- Mechanical parts\n- Electronics\n- Heating systems\n- Plastic processing\n- Safety testing\n\nChina's advantage is the depth of its supporting industries.\n\nA factory is not only choosing workers.\n\nIt is choosing an entire ecosystem.\n\n---\n\n## Faster Product Development Is a Major Advantage\n\nFor many brands, the challenge is not only manufacturing.\n\nIt is product development.\n\nA buyer may start with an idea:\n\n'I want to create a better coffee kettle.'\n\nThen many questions appear:\n\n- What material should be used?\n- How should the heating system work?\n- How can the product pass certification?\n- How can the design reduce production problems?\n\nFactories with strong engineering experience can help answer these questions.\n\nThis is one reason many brands work with experienced [China kitchen appliance OEM manufacturers](https://www.yolec-electronics.com/) instead of only searching for the cheapest supplier.\n\n---\n\n## China Supports Different Business Models\n\nOne reason global brands choose China is flexibility.\n\nDifferent businesses need different solutions.\n\n### Large Retail Brands\n\nThey may need:\n\n- Custom designs\n- Exclusive molds\n- Large production capacity\n- Strict quality systems\n\n### New Brands\n\nThey may prefer:\n\n- Existing product platforms\n- Small trial orders\n- Faster market testing\n\n### Distributors\n\nThey may need:\n\n- Stable supply\n- Competitive pricing\n- Product variety\n\nA good manufacturer can often support different cooperation models.\n\n---\n\n## OEM and ODM Make Market Entry Easier\n\nMany companies do not want to start from zero.\n\nDeveloping a completely new appliance requires time and investment.\n\nODM manufacturing allows brands to start with existing product solutions and customize them.\n\nCommon ODM options include:\n\n- Brand logo\n- Product color\n- Packaging design\n- User manual\n- Market-specific adjustments\n\nFor new brands, this can significantly reduce development risk.\n\n---\n\n## Quality Control Is One of the Biggest Differences Between Factories\n\nA common misunderstanding is:\n\n'Chinese suppliers are all about low price.'\n\nThe reality is that manufacturing quality varies greatly.\n\nThere are factories focused only on reducing cost.\n\nThere are also factories investing heavily in:\n\n- Testing equipment\n- Production control\n- Engineering teams\n- Supplier management\n\nWhen selecting a supplier, buyers should ask:\n\n- How do you inspect incoming materials?\n- What tests are performed before shipment?\n- How do you handle production defects?\n- Can you provide inspection reports?\n\nThe answers usually reveal the real manufacturing level.\n\n---\n\n## Export Experience Makes Communication Easier\n\nProducing a product is one thing.\n\nExporting successfully is another.\n\nInternational buyers often need support with:\n\n- Certification requirements\n- Packaging regulations\n- Shipping documents\n- Country-specific standards\n\nA factory with export experience usually understands these details better.\n\nThis can save weeks of communication.\n\n---\n\n## The Best Factory Is Not Always the Biggest Factory\n\nMany buyers think:\n\n'Bigger factory means better supplier.'\n\nNot necessarily.\n\nA huge manufacturer may focus mainly on large customers.\n\nA specialized factory may provide:\n\n- Faster communication\n- More flexible customization\n- Better attention to smaller brands\n\nThe right supplier depends on your business stage.\n\n---\n\n## What Global Brands Usually Look for in a Chinese Manufacturer\n\nMost successful buyers evaluate suppliers based on several factors:\n\n### Product Experience\n\nDoes the factory understand your category?\n\n### Engineering Ability\n\nCan they solve problems during development?\n\n### Quality Control\n\nDo they have a reliable process?\n\n### Communication\n\nCan they understand your requirements?\n\n### Long-Term Cooperation\n\nCan they support future products?\n\nPrice is important, but it is only one part of the decision.\n\n---\n\n## Final Thoughts\n\nGlobal brands continue sourcing kitchen appliances from China because China offers more than manufacturing capacity.\n\nThe real advantages are:\n\n- Complete supply chain\n- Engineering experience\n- OEM and ODM flexibility\n- Faster product development\n- Mature export systems\n\nOther manufacturing regions are growing, and many companies are building diversified supply chains.\n\nBut for customized small kitchen appliances, China's manufacturing ecosystem remains difficult to replace.\n\nChoosing the right factory is not about finding the cheapest supplier.\n\nIt is about finding a partner that can consistently deliver products your customers will trust.\n\n---\n\nFor buyers researching [OEM and ODM kitchen appliance manufacturing solutions](https://www.yolec-electronics.com/), understanding factory capability, production experience, and quality systems is the first step before starting a project.\n\n---\n\n## About YOLEC Electric\n\nYOLEC Electric specializes in OEM and ODM manufacturing for small kitchen appliances.\n\nOur product categories include:\n\n- Electric kettles\n- Gooseneck coffee kettles\n- Rice cookers\n- Electric pressure cookers\n- Electric lunch boxes\n- Hand mixers\n\nWe work with global importers, distributors, and private label brands.\n\nWebsite:\n\nhttps://www.yolec-electronics.com/\n\nEmail:\n\nAdrian@yolec-electronics.com\n\nWhatsApp:\n\n+86 13922332584\u3002", "top": 0, "createdAt": 1783782959, "style": "", "script": "", "head": "", "ogImage": "https://avatars.githubusercontent.com/u/298971764?v=4", "createdDate": "2026-07-11", "dateLabelColor": "#1f883d"}, "P6": {"htmlDir": "docs/post/What Makes a Good Kitchen Appliance Factory in China-.html", "labels": ["documentation"], "postTitle": "What Makes a Good Kitchen Appliance Factory in China?", "postUrl": "post/What%20Makes%20a%20Good%20Kitchen%20Appliance%20Factory%20in%20China-.html", "postSourceUrl": "https://github.com/yoleckitchen/yoleckitchen.github.io/issues/6", "commentNum": 0, "wordCount": 7818, "description": "When sourcing kitchen appliances from China, many buyers face the same problem:\n\nThere are too many suppliers.\n\nSearch 'kitchen appliance factory China' and you will find thousands of results.\n\nMost suppliers look professional:\n\n- Beautiful product photos\n- Long company introductions\n- Many certificates\n- Low prices\n\nBut after you start an OEM or private label project, the differences become clear.\n\nA good kitchen appliance factory is not just a supplier that can make products.\n\nIt should help you reduce risks, solve production problems, and support your brand growth.\n\nThis article shares some practical points that international buyers should check before choosing a Chinese kitchen appliance manufacturer.\n\n---\n\n## 1. A Good Factory Has Experience With Your Product Category\n\nThe first mistake many buyers make is choosing a supplier only because they have a large catalog.\n\nMore products do not always mean more experience.\n\nKitchen appliances involve different technologies.\n\nFor example:\n\nAn electric kettle requires experience with:\n\n- Heating systems\n- Temperature control\n- Stainless steel processing\n- Electrical safety\n\nA rice cooker requires knowledge of:\n\n- Heating plates\n- Inner pot materials\n- Cooking programs\n- Thermal control\n\nA hand mixer requires experience with:\n\n- Motor performance\n- Speed control\n- Noise reduction\n\nA reliable manufacturer usually focuses on several related product categories instead of producing everything.\n\n---\n\n## 2. Check If They Are a Real OEM Kitchen Appliance Factory\n\nMany buyers search for an **OEM kitchen appliance factory in China**, but the first challenge is verifying whether the supplier is actually a manufacturer.\n\nSome companies are factories.\n\nSome are trading companies.\n\nBoth can have value, but the cooperation model is different.\n\nBefore starting a project, ask:\n\n- Where is your production facility located?\n- How many production lines do you have?\n- Do you have your own injection molding or tooling capability?\n- Can I see your production process?\n\nA real manufacturer should be able to explain how the product is made, not only provide a quotation.\n\n---\n\n## 3. Quality Control Is More Important Than the Lowest Price\n\nA common sourcing mistake is choosing the cheapest supplier.\n\nFor kitchen appliances, the cheapest quotation can create bigger costs later.\n\nProblems may include:\n\n- High defect rate\n- Customer complaints\n- Product returns\n- Certification issues\n- Delayed shipments\n\nA reliable factory should have a clear quality control process.\n\nImportant areas include:\n\n### Incoming Material Inspection\n\nChecking:\n\n- Plastic components\n- Stainless steel parts\n- Electronic components\n- Heating elements\n\nbefore production.\n\n---\n\n### Production Quality Control\n\nProblems should be found during manufacturing, not after shipment.\n\nA good factory monitors:\n\n- Assembly process\n- Product function\n- Safety performance\n- Appearance quality\n\n---\n\n### Final Inspection\n\nBefore shipping, products should be checked for:\n\n- Electrical safety\n- Product functions\n- Packaging quality\n- Appearance defects\n\n---\n\n## 4. OEM and ODM Capability Shows Manufacturing Strength\n\nA factory that only follows drawings has limited flexibility.\n\nFor many brands, OEM and ODM capability is important.\n\nA capable manufacturer can support:\n\n- Product customization\n- New colors\n- Logo application\n- Packaging design\n- Product improvement\n- New model development\n\nMany international brands start with ODM products and later develop customized OEM solutions after understanding their market.\n\nThis is a common approach for private label kitchen appliance brands.\n\n---\n\n## 5. Factory Certifications Should Match Your Market\n\nCertificates are important, but buyers should verify them carefully.\n\nDifferent markets require different standards.\n\nExamples:\n\n- CE for Europe\n- UKCA for the UK market\n- ETL for North America\n- CB for international electrical safety\n- LFGB for food contact materials\n\nA professional supplier should understand certification requirements, not simply send certificate files.\n\nBefore placing an order, confirm:\n\n- Is the certificate for this exact model?\n- Is it suitable for my selling country?\n- Does the testing report match the product?\n\n---\n\n## 6. Production Capacity Should Match Your Business Plan\n\nA supplier may handle sample orders well.\n\nThe real test comes when your business grows.\n\nBefore cooperation, ask about:\n\n- Monthly production capacity\n- Number of workers\n- Production lines\n- Peak season lead time\n- Quality inspection staff\n\nA good supplier should support both your first order and future expansion.\n\n---\n\n## 7. Communication Is a Hidden Quality Indicator\n\nMany buyers focus on factory size and price but ignore communication.\n\nIn international sourcing, communication problems often become production problems.\n\nPay attention to whether the supplier:\n\n- Replies clearly\n- Understands your requirements\n- Gives realistic timelines\n- Explains technical issues\n\nA professional manufacturer will sometimes tell you:\n\n'This design needs improvement.'\n\nor:\n\n'This change will increase cost.'\n\nThat kind of honesty is valuable.\n\n---\n\n## 8. Factory Audit Helps Verify Supplier Capability\n\nPhotos and websites only show part of the picture.\n\nA factory audit can help buyers understand:\n\n- Production conditions\n- Equipment\n- Quality system\n- Warehouse management\n- Manufacturing capability\n\nFor buyers who cannot visit China, online factory inspections and video tours are also useful.\n\nMany international buyers use supplier verification methods before choosing a long-term manufacturing partner.\n\n---\n\n## 9. China vs Southeast Asia: Why Many Brands Still Choose China\n\nSome buyers compare China with Vietnam, Thailand, and other Southeast Asian manufacturing locations.\n\nThese countries have become important alternatives.\n\nHowever, for small kitchen appliances, China still has strong advantages.\n\nThe reason is not only cost.\n\nIt is the complete supply chain.\n\nA kitchen appliance factory needs access to:\n\n- Electronic components\n- Plastic suppliers\n- Metal processing\n- Packaging suppliers\n- Testing services\n\nChina has built a mature ecosystem around these industries.\n\nFor products requiring customization and fast development, this ecosystem can save significant time.\n\n---\n\n## 10. Look for a Manufacturing Partner, Not Just a Supplier\n\nThe best suppliers are not always the ones with the lowest quotation.\n\nA reliable kitchen appliance manufacturer should help you with:\n\n- Product development\n- Quality improvement\n- Production planning\n- Market requirements\n- Long-term cooperation\n\nFor buyers researching [China kitchen appliance OEM and ODM manufacturing solutions](https://www.yolec-electronics.com/), understanding factory capability before cooperation can prevent many common sourcing problems.\n\n---\n\n## Final Checklist Before Choosing a Kitchen Appliance Factory\n\nBefore placing an order, check:\n\n\u2705 Product category experience  \n\u2705 OEM/ODM capability  \n\u2705 Quality control system  \n\u2705 Factory production capability  \n\u2705 Certification knowledge  \n\u2705 Export experience  \n\u2705 Communication quality  \n\nChoosing the right factory at the beginning can save much more time and money later.\n\n---\n\n## About YOLEC Electric\n\nYOLEC Electric is a China-based OEM and ODM manufacturer specializing in small kitchen appliances.\n\nOur production experience includes:\n\n- Electric kettles\n- Gooseneck coffee kettles\n- Rice cookers\n- Electric pressure cookers\n- Electric lunch boxes\n- Hand mixers\n\nWe support global importers, distributors, and private label brands with customized manufacturing solutions.\n\nLearn more about our [China kitchen appliance manufacturer and OEM solutions](https://www.yolec-electronics.com/).\n\nWebsite:\n\nhttps://www.yolec-electronics.com/\n\nEmail:\n\nAdrian@yolec-electronics.com\n\nWhatsApp:\n\n+86 13922332584\u3002", "top": 0, "createdAt": 1783957546, "style": "", "script": "", "head": "", "ogImage": "https://avatars.githubusercontent.com/u/298971764?v=4", "createdDate": "2026-07-13", "dateLabelColor": "#1f883d"}, "P7": {"htmlDir": "docs/post/How to Evaluate a Chinese Supplier Before Placing an Order.html", "labels": ["documentation"], "postTitle": "How to Evaluate a Chinese Supplier Before Placing an Order", "postUrl": "post/How%20to%20Evaluate%20a%20Chinese%20Supplier%20Before%20Placing%20an%20Order.html", "postSourceUrl": "https://github.com/yoleckitchen/yoleckitchen.github.io/issues/7", "commentNum": 0, "wordCount": 8383, "description": "Finding a supplier in China is easy.\n\nFinding a supplier you can trust is the real challenge.\n\nMost international buyers start with online platforms and search:\n\n'Chinese supplier'\n\n'China manufacturer'\n\n'OEM factory China'\n\nWithin a few minutes, they can find hundreds of companies offering similar products.\n\nThe problem is that supplier websites usually show the best side:\n\n- Professional factory photos\n- Product catalogs\n- Certifications\n- Low prices\n\nBut these things do not always tell you how the supplier performs after receiving your order.\n\nBefore placing an order with a Chinese supplier, you need to evaluate several important factors.\n\nThis is especially true for products like kitchen appliances, where quality issues can directly affect customer reviews, returns, and your brand reputation.\n\n---\n\n## 1. Verify If the Supplier Is a Real Manufacturer\n\nThe first step in supplier verification is confirming who you are actually working with.\n\nMany overseas buyers search for:\n\n'China manufacturer'\n\nbut some suppliers are actually trading companies.\n\nTrading companies are not necessarily bad.\n\nThey can be useful when you need multiple product categories.\n\nHowever, for OEM and private label projects, many buyers prefer working directly with factories.\n\nA real manufacturer should be able to explain:\n\n- Production process\n- Factory location\n- Manufacturing equipment\n- Production capacity\n- Quality control procedures\n\nSimple questions can reveal a lot:\n\n- Do you own the factory?\n- How many production lines do you have?\n- Can you show your production workshop?\n- Do you manufacture this product category regularly?\n\nA reliable supplier usually provides clear answers.\n\n---\n\n## 2. Check Supplier Experience in Your Product Category\n\nOne common mistake is choosing suppliers based only on product pictures.\n\nA supplier may show hundreds of products.\n\nBut that does not mean they have deep experience.\n\nFor kitchen appliances, category experience matters.\n\nFor example:\n\nAn electric kettle manufacturer should understand:\n\n- Heating system design\n- Temperature control\n- Safety protection\n- Stainless steel processing\n\nA rice cooker manufacturer should understand:\n\n- Heating performance\n- Inner pot materials\n- Control systems\n\nA hand mixer manufacturer should understand:\n\n- Motor performance\n- Speed control\n- Product durability\n\nWhen evaluating suppliers, always ask:\n\n'How many years have you been producing this product?'\n\n---\n\n## 3. Review Factory Capability Before Ordering\n\nA supplier can have a good sales team.\n\nBut production capability determines whether your order succeeds.\n\nBefore cooperation, check:\n\n### Production Capacity\n\nAsk about:\n\n- Monthly production output\n- Number of workers\n- Assembly lines\n- Normal lead time\n\n### Manufacturing Resources\n\nDepending on the product, check whether they have:\n\n- Injection molding capability\n- Assembly workshops\n- Testing equipment\n- Engineering support\n\nFor example, when sourcing [OEM kitchen appliances from China](https://www.yolec-electronics.com/), buyers should evaluate not only the product itself but also whether the factory has the production resources to support long-term cooperation.\n\n---\n\n## 4. Evaluate Quality Control System\n\nMany suppliers say:\n\n'We have strict quality control.'\n\nThe important question is:\n\n'What does your quality control process actually include?'\n\nA reliable factory normally controls quality at different stages.\n\n### Incoming Material Inspection\n\nBefore production:\n\n- Plastic components\n- Metal parts\n- Electronic components\n- Heating elements\n\nshould be inspected.\n\n---\n\n### Production Inspection\n\nDuring assembly:\n\n- Product function\n- Electrical safety\n- Assembly accuracy\n- Appearance quality\n\nshould be monitored.\n\n---\n\n### Final Inspection\n\nBefore shipment:\n\n- Product testing\n- Packaging check\n- Random inspection\n\nshould be completed.\n\nA good supplier does not depend only on final inspection.\n\nThey prevent problems during production.\n\n---\n\n## 5. Request Samples and Test Before Bulk Orders\n\nNever place a large order based only on:\n\n- Product photos\n- Videos\n- Catalogs\n\nSamples are one of the most important steps in supplier evaluation.\n\nFor kitchen appliances, check:\n\n### Product Performance\n\n- Heating speed\n- Noise level\n- Temperature accuracy\n- User experience\n\n### Product Quality\n\n- Material quality\n- Assembly details\n- Surface finishing\n\n### Packaging\n\n- Protection during transportation\n- Retail appearance\n\nA sample can reveal problems that are impossible to see online.\n\n---\n\n## 6. Verify Certifications for Your Target Market\n\nMany buyers ask:\n\n'Does this supplier have certificates?'\n\nThis is not enough.\n\nThe correct question is:\n\n'Does this exact product have the certification required for my market?'\n\nDepending on your country, you may need:\n\n- CE\n- CB\n- GS\n- ETL\n- UKCA\n- RoHS\n- LFGB\n\nAlways confirm:\n\n- Product model\n- Testing standard\n- Certificate validity\n- Target market requirements\n\nCertification problems discovered after production can become very expensive.\n\n---\n\n## 7. Evaluate Communication Before You Pay\n\nCommunication is one of the easiest ways to judge a supplier.\n\nBefore placing an order, notice:\n\nDoes the supplier:\n\n- Ask detailed questions?\n- Understand your requirements?\n- Explain possible problems?\n- Provide realistic delivery dates?\n\nBe careful with suppliers who answer every question with:\n\n'Yes, no problem.'\n\nProfessional manufacturers know that every project has limitations.\n\nSometimes a supplier saying:\n\n'This design needs improvement'\n\nis actually a good sign.\n\n---\n\n## 8. Check OEM and ODM Capability\n\nMany brands today are not only looking for ready-made products.\n\nThey want:\n\n- Private label products\n- Custom packaging\n- Brand differentiation\n- Product improvements\n\nThis is why OEM and ODM capability is important.\n\nA capable supplier should support:\n\n- Logo customization\n- Color changes\n- Packaging development\n- Product modification\n- New model development\n\nFor buyers building a kitchen appliance brand, choosing a factory with both OEM and ODM experience can make future product expansion easier.\n\n---\n\n## 9. Understand Supplier Export Experience\n\nA factory may produce good products.\n\nBut international export requires additional experience.\n\nA reliable export supplier should understand:\n\n- Shipping documents\n- International packaging requirements\n- Certification documents\n- Different market standards\n\nThis is especially important for buyers importing kitchen appliances into Europe, North America, and other regulated markets.\n\n---\n\n## 10. Consider Factory Audit Before Large Orders\n\nFor first-time cooperation, supplier verification is worth the effort.\n\nA factory audit can help check:\n\n- Production environment\n- Equipment condition\n- Quality management\n- Employee organization\n- Warehouse operation\n\nIf you cannot visit China personally, a video factory inspection is also useful.\n\n---\n\n## China Supplier Evaluation Checklist\n\nBefore placing your first order, check:\n\n\u2705 Is this a real manufacturer?  \n\u2705 Do they have experience with my product category?  \n\u2705 Can they provide samples?  \n\u2705 Do they have quality control procedures?  \n\u2705 Can they support OEM/ODM customization?  \n\u2705 Do they understand my target market?  \n\u2705 Can they handle future orders?  \n\u2705 Is communication reliable?\n\n---\n\n## Final Thoughts\n\nChoosing a Chinese supplier is not only about finding a good price.\n\nThe real goal is reducing risk.\n\nA reliable supplier should provide:\n\n- Stable production\n- Consistent quality\n- Clear communication\n- Technical support\n- Long-term cooperation\n\nTaking time to evaluate suppliers before placing an order can prevent expensive problems later.\n\nFor companies researching [China kitchen appliance manufacturers and OEM suppliers](https://www.yolec-electronics.com/), understanding factory capability and supplier verification methods is the first step before starting cooperation.\n\n---\n\n## About YOLEC Electric\n\nYOLEC Electric specializes in OEM and ODM manufacturing of small kitchen appliances.\n\nProduct categories include:\n\n- Electric kettles\n- Gooseneck coffee kettles\n- Rice cookers\n- Electric pressure cookers\n- Electric lunch boxes\n- Hand mixers\n\nWe support global importers, distributors, and private label brands with customized manufacturing solutions.\n\nWebsite:\n\nhttps://www.yolec-electronics.com/\n\nEmail:\n\nAdrian@yolec-electronics.com\n\nWhatsApp:\n\n+86 13922332584\u3002", "top": 0, "createdAt": 1784109022, "style": "", "script": "", "head": "", "ogImage": "https://avatars.githubusercontent.com/u/298971764?v=4", "createdDate": "2026-07-15", "dateLabelColor": "#1f883d"}}, "singeListJson": {}, "labelColorDict": {"bug": "#d73a4a", "documentation": "#0075ca", "duplicate": "#cfd3d7", "enhancement": "#a2eeef", "good first issue": "#7057ff", "help wanted": "#008672", "invalid": "#e4e669", "question": "#d876e3", "wontfix": "#ffffff"}, "faviconUrl": "https://avatars.githubusercontent.com/u/298971764?v=4", "ogImage": "https://avatars.githubusercontent.com/u/298971764?v=4", "primerCSS": "<link href='https://mirrors.sustech.edu.cn/cdnjs/ajax/libs/Primer/21.0.7/primer.css' rel='stylesheet' />", "prevUrl": "disabled", "nextUrl": "disabled"}